emtransmission/__init__.py
emtransmission/fk_recoding.py
emtransmission/fk_recoding_snap.py
emtransmission/fk_recoding_without_graphic.py
emtransmission-2.1.0.dist-info/LICENSE
emtransmission-2.1.0.dist-info/METADATA
emtransmission-2.1.0.dist-info/WHEEL
emtransmission-2.1.0.dist-info/top_level.txt
emtransmission-2.1.0.dist-info/RECORD
