Metadata-Version: 2.1
Name: emtransmission
Version: 2.1.0
Summary: Electric Monitoring System for image sensor
Author-email: Taehoon Koh <thkoh@suncom.co.kr>, Yonghoon Kim <kimyhjava@pukyong.ac.kr>
Project-URL: Homepage, https://github.com/pypa/sampleproject
Project-URL: Bug Tracker, https://github.com/pypa/sampleproject/issues
Classifier: Programming Language :: Python :: 3
Classifier: License :: OSI Approved :: MIT License
Classifier: Operating System :: OS Independent
Requires-Python: >=3.9
License-File: LICENSE
